MANIFEST.in
README.rst
setup.py
cmsplugin_htmlsitemap/__init__.py
cmsplugin_htmlsitemap/cms_plugins.py
cmsplugin_htmlsitemap/models.py
cmsplugin_htmlsitemap.egg-info/PKG-INFO
cmsplugin_htmlsitemap.egg-info/SOURCES.txt
cmsplugin_htmlsitemap.egg-info/dependency_links.txt
cmsplugin_htmlsitemap.egg-info/not-zip-safe
cmsplugin_htmlsitemap.egg-info/top_level.txt
cmsplugin_htmlsitemap/locale/de/LC_MESSAGES/django.mo
cmsplugin_htmlsitemap/locale/de/LC_MESSAGES/django.po
cmsplugin_htmlsitemap/migrations/0001_initial.py
cmsplugin_htmlsitemap/migrations/0002_auto__add_field_htmlsitemap_match_language.py
cmsplugin_htmlsitemap/migrations/__init__.py
cmsplugin_htmlsitemap/templates/cmsplugin_htmlsitemap/sitemap.html