Metadata-Version: 1.1
Name: cmsplugin-htmlsitemap
Version: 0.1.4
Summary: HTML sitemap plugin for Django CMS
Home-page: https://github.com/raphaa/cmsplugin-htmlsitemap
Author: Raphael Jasjukaitis
Author-email: hello@raphael-jasjukaitis.de
License: UNKNOWN
Platform: UNKNOWN
Classifier: Environment :: Web Environment
Classifier: License :: OSI Approved :: BSD License
Classifier: Operating System :: OS Independent
Classifier: Programming Language :: Python
Classifier: Framework :: Django
